[
    {
        "id": "1",
        "name": "Shiny Dio Overheaven",
        "rarity": "High SSS",
        "image": "images/ShinyDio.png",
        "demand": "4",
        "value": "Owners Choice",
        "trend": "Overpriced"
    },
    {
        "id": "3",
        "name": "Dio Overheaven",
        "rarity": "SS",
        "image": "images/Dio.png",
        "demand": "6.5",
        "value": 36000,
        "trend": "Overpriced"
    },
    {
        "id": "4",
        "name": "Gohan",
        "rarity": "SS",
        "image": "images/Gohan.png",
        "demand": "5.5",
        "value": 32000,
        "trend": "Stable"
    }
    
]